osservaprezzi/.DS_Store
osservaprezzi/__init__.py
osservaprezzi/client.py
osservaprezzi/const.py
osservaprezzi/exceptions.py
osservaprezzi/helpers.py
osservaprezzi/models.py
osservaprezzi/py.typed
osservaprezzi-0.1.5.dist-info/LICENSE
osservaprezzi-0.1.5.dist-info/METADATA
osservaprezzi-0.1.5.dist-info/WHEEL
osservaprezzi-0.1.5.dist-info/top_level.txt
osservaprezzi-0.1.5.dist-info/RECORD
