Metadata-Version: 2.1
Name: osservaprezzi
Version: 0.1.5
Summary: Python library for Osservaprezzi Carburanti 
Author-email: Lorenzo Monaco <lnx85@lnxlabs.it>
License: GPL-3.0
Project-URL: Homepage, https://github.com/lnx85/osservaprezzi.py
Project-URL: Source Code, https://github.com/lnx85/osservaprezzi.py
Project-URL: Bug Reports, https://github.com/lnx85/osservaprezzi.py/issues
Keywords: osservaprezzi,carburanti,mise
Classifier: Development Status :: 4 - Beta
Classifier: Intended Audience :: Developers
Classifier: License :: OSI Approved :: GNU General Public License v3 (GPLv3)
Classifier: Programming Language :: Python :: 3.12
Classifier: Topic :: Software Development :: Libraries :: Python Modules
Requires-Python: >=3.12.0
License-File: LICENSE
Requires-Dist: aiohttp ~=3.9
